pyspatialstats/__init__.py
pyspatialstats/enums.py
pyspatialstats/utils.py
pyspatialstats/views.py
pyspatialstats/windows.py
pyspatialstats/bootstrap/__init__.py
pyspatialstats/bootstrap/config.py
pyspatialstats/bootstrap/linear_regression.c
pyspatialstats/bootstrap/linear_regression.cp311-win_amd64.pyd
pyspatialstats/bootstrap/linear_regression.pxd
pyspatialstats/bootstrap/linear_regression.pyx
pyspatialstats/bootstrap/mean.c
pyspatialstats/bootstrap/mean.cp311-win_amd64.pyd
pyspatialstats/bootstrap/mean.pxd
pyspatialstats/bootstrap/mean.pyx
pyspatialstats/focal/__init__.py
pyspatialstats/focal/_core.py
pyspatialstats/focal/correlation.py
pyspatialstats/focal/function.py
pyspatialstats/focal/linear_regression.py
pyspatialstats/focal/majority.py
pyspatialstats/focal/max.py
pyspatialstats/focal/mean.py
pyspatialstats/focal/min.py
pyspatialstats/focal/std.py
pyspatialstats/focal/sum.py
pyspatialstats/focal/utils.py
pyspatialstats/focal/core/__init__.py
pyspatialstats/focal/core/correlation.c
pyspatialstats/focal/core/correlation.cp311-win_amd64.pyd
pyspatialstats/focal/core/correlation.pyx
pyspatialstats/focal/core/linear_regression.c
pyspatialstats/focal/core/linear_regression.cp311-win_amd64.pyd
pyspatialstats/focal/core/linear_regression.pyx
pyspatialstats/focal/core/majority.c
pyspatialstats/focal/core/majority.cp311-win_amd64.pyd
pyspatialstats/focal/core/majority.pyx
pyspatialstats/focal/core/max.c
pyspatialstats/focal/core/max.cp311-win_amd64.pyd
pyspatialstats/focal/core/max.pyx
pyspatialstats/focal/core/mean.c
pyspatialstats/focal/core/mean.cp311-win_amd64.pyd
pyspatialstats/focal/core/mean.pyx
pyspatialstats/focal/core/min.c
pyspatialstats/focal/core/min.cp311-win_amd64.pyd
pyspatialstats/focal/core/min.pyx
pyspatialstats/focal/core/std.c
pyspatialstats/focal/core/std.cp311-win_amd64.pyd
pyspatialstats/focal/core/std.pyx
pyspatialstats/focal/core/sum.c
pyspatialstats/focal/core/sum.cp311-win_amd64.pyd
pyspatialstats/focal/core/sum.pyx
pyspatialstats-0.1.1.dist-info/licenses/LICENSE
pyspatialstats-0.1.1.dist-info/METADATA
pyspatialstats-0.1.1.dist-info/WHEEL
pyspatialstats-0.1.1.dist-info/top_level.txt
pyspatialstats-0.1.1.dist-info/RECORD
