Metadata-Version: 2.4
Name: pyspatialstats
Version: 0.1.1
Author-email: Jasper Roebroek <roebroek.jasper@gmail.com>
License: MIT
Project-URL: repository, https://github.com/jasperroebroek/pyspatialstats
Project-URL: documentation, https://pyspatialstats.readthedocs.io/en/latest/index.html
Requires-Python: >=3.10
License-File: LICENSE
Requires-Dist: numpy>=2.2.1
Requires-Dist: joblib
Requires-Dist: pandas
Requires-Dist: scipy
Provides-Extra: documentation
Requires-Dist: sphinx; extra == "documentation"
Requires-Dist: sphinx_rtd_theme; extra == "documentation"
Requires-Dist: numpydoc; extra == "documentation"
Requires-Dist: jupyter; extra == "documentation"
Requires-Dist: matplotlib; extra == "documentation"
Requires-Dist: rasterio; extra == "documentation"
Provides-Extra: develop
Requires-Dist: cython; extra == "develop"
Requires-Dist: sphinx; extra == "develop"
Requires-Dist: sphinx_rtd_theme; extra == "develop"
Requires-Dist: numpydoc; extra == "develop"
Requires-Dist: jupyter; extra == "develop"
Requires-Dist: matplotlib; extra == "develop"
Requires-Dist: pytest; extra == "develop"
Requires-Dist: joblib; extra == "develop"
Requires-Dist: statsmodels; extra == "develop"
Requires-Dist: rasterio; extra == "develop"
Provides-Extra: test
Requires-Dist: pytest; extra == "test"
Requires-Dist: statsmodels; extra == "test"
Requires-Dist: scikit-learn; extra == "test"
Requires-Dist: xarray; extra == "test"
Dynamic: license-file
